automua/__init__.py
automua/config.py
automua/database.py
automua/ldap.py
automua/model.py
automua/server.py
automua/util.py
automua/generators/__init__.py
automua/generators/apple.py
automua/generators/mozilla.py
automua/generators/outlook.py
automua/views/__init__.py
automua/views/autoconfig.py
automua/views/autodiscover.py
automua/views/initdb.py
automua/views/mobileconfig.py
automua/views/site.py
automua-2023.0.dist-info/METADATA
automua-2023.0.dist-info/WHEEL
automua-2023.0.dist-info/licenses/COPYING
automua-2023.0.dist-info/RECORD
