Metadata-Version: 2.1
Name: automua
Version: 2023.0
Summary: Mail client autoconfiguration service
Project-URL: Homepage, https://hlfh.github.io/automua
Project-URL: Tracker, https://github.com/hlfh/automua/issues
Project-URL: Source, https://github.com/hlfh/automua
Author-email: Gaspard d'Hautefeuille <contact@hlfh.space>
License-File: COPYING
Classifier: Development Status :: 5 - Production/Stable
Classifier: License :: OSI Approved :: GNU General Public License v3 or later (GPLv3+)
Classifier: Operating System :: OS Independent
Classifier: Programming Language :: Python :: 3
Requires-Python: >=3.7
Requires-Dist: alembic==1.9.1
Requires-Dist: flask-migrate==4.0.0
Requires-Dist: flask-sqlalchemy==3.0.2
Requires-Dist: flask==2.2.2
Requires-Dist: ldap3==2.9.1
Requires-Dist: lxml==4.9.2
Requires-Dist: sqlalchemy==2.0.0rc1
Requires-Dist: werkzeug==2.2.2
Provides-Extra: deploy
Requires-Dist: coverage==7.0.2; extra == 'deploy'
Requires-Dist: flake8==6.0.0; extra == 'deploy'
Requires-Dist: hatch==1.6.3; extra == 'deploy'
Requires-Dist: pip-tools==6.12.1; extra == 'deploy'
Provides-Extra: test
Requires-Dist: pytest-flask==1.2.0; extra == 'test'
Requires-Dist: pytest==7.2.0; extra == 'test'
